m3ufu.py
m3ufu-0.0.97.data/scripts/m3ufu
m3ufu-0.0.97.dist-info/LICENSE
m3ufu-0.0.97.dist-info/METADATA
m3ufu-0.0.97.dist-info/WHEEL
m3ufu-0.0.97.dist-info/top_level.txt
m3ufu-0.0.97.dist-info/RECORD
