Metadata-Version: 2.1
Name: m3ufu
Version: 0.0.97
Summary: M3U8 Parser with SCTE-35 Support
Home-page: https://github.com/superkabuki/m3u8fu
Author: Adrian
Author-email: spam@iodisco.com
Classifier: License :: OSI Approved :: MIT License
Classifier: Operating System :: OS Independent
Classifier: Programming Language :: Python :: 3.6
Classifier: Programming Language :: Python :: Implementation :: PyPy
Classifier: Programming Language :: Python :: Implementation :: CPython
Requires-Python: >=3.6
License-File: LICENSE
Requires-Dist: pyaes
Requires-Dist: threefive (>=3.0.59)
